config/__init__.py
config/configuration.py
stripe_webhook_parser/__init__.py
stripe_webhook_parser/events.py
stripe_webhook_parser/webhooks.py
stripe_Webhook-0.0.1.dist-info/LICENCE
stripe_Webhook-0.0.1.dist-info/METADATA
stripe_Webhook-0.0.1.dist-info/WHEEL
stripe_Webhook-0.0.1.dist-info/top_level.txt
stripe_Webhook-0.0.1.dist-info/RECORD
