Metadata-Version: 2.1
Name: stripe-Webhook
Version: 0.0.1
Summary: a package for stripe webhook
Home-page: https://gitlab.com/maximeV/nowhatstripet
Author: maximeV
Author-email: vermande.maxime@gmail.com
License: UNKNOWN
Platform: UNKNOWN
Classifier: Programming Language :: Python :: 3
Classifier: License :: OSI Approved :: MIT License
Classifier: Operating System :: OS Independent
